arts_tools/__init__.py
arts_tools/__version__.py
arts_tools/constants.py
arts_tools/tools.py
arts_tools/archive/__init__.py
arts_tools/archive/download_from_alta.py
arts_tools/archive/download_helpers.py
arts_tools/fits/__init__.py
arts_tools/fits/fix_file_from_before_20200408.py
arts_tools/fits/reader.py
arts_tools/iquv/__init__.py
arts_tools/iquv/psrdada_to_fits.py
arts_tools/pulsars/__init__.py
arts_tools/pulsars/find_pulsars.py
arts_tools/static/sbtable-sc4-12tabs-71sbs.txt
arts_tools/static/square_39p1.cb_offsets
arts_tools/static/fits_templates/sc3_IQUV.txt
arts_tools/static/fits_templates/sc4_IQUV.txt
arts_tools-1.5.5.data/scripts/arts_read_parameterset
arts_tools-1.5.5.dist-info/LICENSE
arts_tools-1.5.5.dist-info/METADATA
arts_tools-1.5.5.dist-info/WHEEL
arts_tools-1.5.5.dist-info/entry_points.txt
arts_tools-1.5.5.dist-info/top_level.txt
arts_tools-1.5.5.dist-info/RECORD
