Metadata-Version: 2.1
Name: arts-tools
Version: 1.5.5
Summary: Tools to read or process ARTS data
Home-page: http://github.com/loostrum/arts_tools
Author: Leon Oostrum
Author-email: l.oostrum@esciencecenter.nl
License: Apache2.0
Platform: UNKNOWN
Classifier: License :: OSI Approved :: Apache Software License
Classifier: Programming Language :: Python :: 3
Classifier: Operating System :: OS Independent
Requires-Python: >=3.6
Requires-Dist: numpy (>=1.17)
Requires-Dist: astropy
Requires-Dist: psrqpy
Requires-Dist: tqdm
Provides-Extra: irods
Requires-Dist: python-irodsclient ; extra == 'irods'
